swiftsimio/__cite__.py
swiftsimio/__init__.py
swiftsimio/__version__.py
swiftsimio/_array_functions.py
swiftsimio/_handle_provider.py
swiftsimio/accelerated.py
swiftsimio/conversions.py
swiftsimio/masks.py
swiftsimio/objects.py
swiftsimio/optional_packages.py
swiftsimio/reader.py
swiftsimio/snapshot_writer.py
swiftsimio/statistics.py
swiftsimio/subset_writer.py
swiftsimio/swiftsnap.py
swiftsimio/units.py
swiftsimio/metadata/__init__.py
swiftsimio/metadata/objects.py
swiftsimio/metadata/cosmology/__init__.py
swiftsimio/metadata/cosmology/cosmology_fields.py
swiftsimio/metadata/metadata/__init__.py
swiftsimio/metadata/metadata/metadata_fields.py
swiftsimio/metadata/particle/__init__.py
swiftsimio/metadata/particle/particle_fields.py
swiftsimio/metadata/particle/particle_types.py
swiftsimio/metadata/soap/__init__.py
swiftsimio/metadata/soap/soap_types.py
swiftsimio/metadata/unit/__init__.py
swiftsimio/metadata/unit/unit_fields.py
swiftsimio/metadata/unit/unit_types.py
swiftsimio/metadata/writer/__init__.py
swiftsimio/metadata/writer/required_fields.py
swiftsimio/visualisation/__init__.py
swiftsimio/visualisation/_vistools.py
swiftsimio/visualisation/power_spectrum.py
swiftsimio/visualisation/projection.py
swiftsimio/visualisation/rotation.py
swiftsimio/visualisation/slice.py
swiftsimio/visualisation/volume_render.py
swiftsimio/visualisation/projection_backends/__init__.py
swiftsimio/visualisation/projection_backends/fast.py
swiftsimio/visualisation/projection_backends/gpu.py
swiftsimio/visualisation/projection_backends/histogram.py
swiftsimio/visualisation/projection_backends/kernels.py
swiftsimio/visualisation/projection_backends/reference.py
swiftsimio/visualisation/projection_backends/renormalised.py
swiftsimio/visualisation/projection_backends/subsampled.py
swiftsimio/visualisation/projection_backends/subsampled_extreme.py
swiftsimio/visualisation/slice_backends/__init__.py
swiftsimio/visualisation/slice_backends/nearest_neighbours.py
swiftsimio-11.0.0.dist-info/licenses/COPYING
swiftsimio-11.0.0.dist-info/licenses/COPYING.LESSER
swiftsimio-11.0.0.dist-info/METADATA
swiftsimio-11.0.0.dist-info/WHEEL
swiftsimio-11.0.0.dist-info/entry_points.txt
swiftsimio-11.0.0.dist-info/top_level.txt
swiftsimio-11.0.0.dist-info/RECORD
