Metadata-Version: 2.4
Name: swiftsimio
Version: 11.0.0
Summary: SWIFTsim (swiftsim.com) i/o routines for python.
Author-email: Josh Borrow <josh@joshborrow.com>
Project-URL: Homepage, https://github.com/SWIFTSIM/swiftsimio
Project-URL: Bug Tracker, https://github.com/SWIFTSIM/swiftsimio/issues
Project-URL: Documentation, https://swiftsimio.readthedocs.io
Classifier: Programming Language :: Python :: 3.10
Classifier: Programming Language :: Python :: 3.11
Classifier: Programming Language :: Python :: 3.12
Classifier: Programming Language :: Python :: 3.13
Classifier: License :: OSI Approved :: GNU Lesser General Public License v3 or later (LGPLv3+)
Classifier: Operating System :: OS Independent
Requires-Python: >3.10.0
License-File: COPYING
License-File: COPYING.LESSER
Requires-Dist: astropy>=6.0
Requires-Dist: numpy>=2.1.0
Requires-Dist: h5py
Requires-Dist: unyt>=3.1.0
Requires-Dist: numba>=0.50.0
Provides-Extra: dev
Requires-Dist: pytest; extra == "dev"
Requires-Dist: ruff; extra == "dev"
Requires-Dist: numpydoc; extra == "dev"
Requires-Dist: matplotlib; extra == "dev"
Requires-Dist: scipy; extra == "dev"
Requires-Dist: wily; extra == "dev"
Provides-Extra: docs
Requires-Dist: sphinx; extra == "docs"
Requires-Dist: sphinx-rtd-theme; extra == "docs"
Requires-Dist: recommonmark; extra == "docs"
Requires-Dist: sphinx_design; extra == "docs"
Provides-Extra: all
Requires-Dist: swiftsimio[dev,docs]; extra == "all"
Dynamic: license-file
